<?xml version="1.0" encoding="utf-8"?>
<window type="dialog" id="1110">
	<visible>Player.Seeking | Player.DisplayAfterSeek | [Player.Paused + !Player.Caching] | Player.Forwarding | Player.Rewinding | Player.ShowInfo | Player.ShowTime | Window.IsActive(videoosd) | Window.IsActive(musicosd) | Window.IsActive(playerprocessinfo) | !String.IsEmpty(Player.SeekNumeric) | !String.IsEmpty(PVR.ChannelNumberInput)</visible>
	<visible>![Window.IsActive(sliderdialog) | Window.IsActive(pvrosdchannels) | Window.IsActive(pvrguideinfo)] + VideoPlayer.Content(LiveTV)</visible>
	<visible>Window.IsActive(fullscreenvideo) | Window.IsActive(visualisation)</visible>
	<include>Animation_BottomSlide</include>
	<depth>DepthOSD</depth>
	<zorder>0</zorder>
	<controls>
		<include>PVRChannelNumberInput</include>
		<control type="group">
			<visible>!Player.HasGame</visible>
			<bottom>0</bottom>
			<height>190</height>
			<control type="image">
				<left>-40</left>
				<width>120%</width>
				<height>200</height>
				<texture flipy="true">frame/osdfade.png</texture>
			</control>
			<control type="group">
				<visible>!Window.IsVisible(videoosd) + !Window.IsVisible(musicosd)</visible>
				<visible>Player.ShowInfo</visible>
				<animation effect="fade" time="200">VisibleChange</animation>
				<control type="image">
					<left>200</left>
					<top>120</top>
					<width>264</width>
					<height>40</height>
					<texture>$INFO[MusicPlayer.UserRating,flags/starrating/,.png]</texture>
					<aspectratio>keep</aspectratio>
				</control>
				<control type="grouplist">
					<right>20</right>
					<top>110</top>
					<width>1000</width>
					<height>100</height>
					<align>right</align>
					<include>Animation_BottomSlide</include>
					<orientation>horizontal</orientation>
					<itemgap>10</itemgap>
					<visible>Player.ShowInfo + !Player.ChannelPreviewActive + Window.IsActive(fullscreenvideo)</visible>
					<animation effect="fade" start="0" end="100" time="200" delay="1000">Visible</animation>
					<include content="MediaFlag">
						<param name="texture" value="$INFO[VideoPlayer.AudioChannels,flags/audiochannel/,.png]" />
					</include>
					<include content="MediaFlag">
						<param name="texture" value="$INFO[VideoPlayer.AudioCodec,flags/audiocodec/,.png]" />
					</include>
					<include content="MediaFlag">
						<param name="texture" value="$INFO[VideoPlayer.VideoAspect,flags/aspectratio/,.png]" />
					</include>
					<include content="MediaFlag">
						<param name="texture" value="$INFO[VideoPlayer.VideoCodec,flags/videocodec/,.png]" />
					</include>
				</control>
				<control type="grouplist">
					<right>20</right>
					<top>110</top>
					<width>1000</width>
					<height>100</height>
					<align>right</align>
					<include>Animation_BottomSlide</include>
					<orientation>horizontal</orientation>
					<itemgap>10</itemgap>
					<visible>Player.ShowInfo + !Player.ChannelPreviewActive + Window.IsActive(visualisation)</visible>
					<animation effect="fade" start="0" end="100" time="200" delay="1000">Visible</animation>
					<include content="MediaFlag">
						<param name="texture" value="$INFO[MusicPlayer.Codec,flags/audiocodec/,.png]" />
					</include>
					<include content="MediaFlag">
						<param name="texture" value="flags/rds/rds.png" />
						<param name="visible" value="RDS.HasRDS" />
					</include>
				</control>
				<control type="group">
					<visible>PVR.IsRecordingPlayingChannel + !Player.ChannelPreviewActive</visible>
					<control type="image">
						<top>100</top>
						<left>20</left>
						<width>74</width>
						<height>74</height>
						<texture>osd/fullscreen/buttons/record.png</texture>
					</control>
					<control type="label">
						<top>110</top>
						<left>90</left>
						<width>400</width>
						<height>50</height>
						<aligny>center</aligny>
						<font>font25_title</font>
						<label>$LOCALIZE[19158]</label>
					</control>
				</control>
				<control type="label">
					<top>110</top>
					<right>20</right>
					<width>400</width>
					<height>50</height>
					<align>right</align>
					<aligny>center</aligny>
					<font>font13</font>
					<wrapmultiline>true</wrapmultiline>
					<animation effect="fade" time="200">VisibleChange</animation>
					<label>$INFO[Player.TimeRemaining,[COLOR button_focus]$LOCALIZE[31134]:[CR][/COLOR]]</label>
					<visible>![Player.ShowInfo | Window.IsVisible(playerprocessinfo) | VideoPlayer.HasEpg]</visible>
				</control>
				<control type="label">
					<top>110</top>
					<right>20</right>
					<width>400</width>
					<height>50</height>
					<align>right</align>
					<aligny>center</aligny>
					<font>font13</font>
					<wrapmultiline>true</wrapmultiline>
					<animation effect="fade" time="200">VisibleChange</animation>
					<label>$INFO[PVR.EpgEventRemainingTime,[COLOR button_focus]$LOCALIZE[31134]:[CR][/COLOR]]</label>
					<visible>![Player.ShowInfo | Window.IsVisible(playerprocessinfo)] + VideoPlayer.HasEpg</visible>
				</control>
			</control>
			<control type="label"><!-- Zeit unten -->
				<centerleft>50%</centerleft>
				<top>110</top>
				<width>50%</width>
				<height>75</height>
				<align>center</align>
				<aligny>bottom</aligny>
				<animation delay="0" effect="slide" time="120" start="0,0" end="0,-20" tween="sine" easing="inout" condition="!String.IsEmpty(Control.GetLabel(40000))">Conditional</animation>
				<label>$VAR[SeekTimeLabelVar]</label>
				<font>font45</font>
				<shadowcolor>black</shadowcolor>
				<visible>!Player.ChannelPreviewActive | VideoPlayer.HasEpg</visible>
				<visible>Player.ShowInfo</visible>
			</control>
			<control type="label" id="40000"> <!-- unter Zeit unten -->
				<centerleft>50%</centerleft>
				<top>-500</top>
				<width>50%</width>
				<height>60</height>
				<align>center</align>
				<aligny>center</aligny>
				<label>$VAR[SeekLabel]</label>
				<shadowcolor>black</shadowcolor>
			</control>
		</control>
		<control type="group">
			<visible>!Window.IsVisible(playerprocessinfo)</visible>
			<visible>Player.ShowInfo</visible>
			<animation effect="fade" time="400">VisibleChange</animation>
			<animation effect="slide" end="0,-20" time="150" condition="VideoPlayer.Content(LiveTV)">conditional</animation>
			<bottom>-38</bottom>
			<height>380</height>
			<control type="image">
				<left>0</left>
				<width>100%</width>
				<height>240</height>
				<texture>dialogs/dialog-bg-nobo.png</texture>
			</control>
			<control type="image">
				<left>30</left>
				<top>30</top>
				<width>200</width>
				<height>200</height>
				<aspectratio aligny="center">keep</aspectratio>
				<texture>$INFO[Player.Icon]</texture>
			</control>
			<control type="label"><!-- ChannelNumber -->
				<left>250</left>
				<width>90</width>
				<font>font45</font>
				<top>0</top>
				<height>20</height>
				<label>$INFO[VideoPlayer.ChannelNumberLabel]</label>
				<shadowcolor>black</shadowcolor>
				<align>right</align>
			</control>
			<control type="label"><!-- Uhrzeit -->
				<font>font_clock</font>
				<shadowcolor>text_shadow</shadowcolor>
				<top>-10</top>
				<left>0</left>
				<height>100</height>
				<width>250</width>
				<align>center</align>
				<label>[B]$INFO[System.Time][/B]</label>
			</control>
			<control type="label"><!-- EPG Titel -->
				<visible>String.IsEmpty(Player.Art(clearlogo))</visible>
				<visible>String.IsEmpty(Player.Art(tvshow.clearlogo))</visible>
				<animation effect="fade" time="150">VisibleChange</animation>
				<label>$VAR[NowPlayingBreadcrumbsVar, - ]</label>
				<font>font45</font>
				<shadowcolor>text_shadow</shadowcolor>
				<top>0</top>
				<height>100</height>
				<left>335</left>
				<right>0</right>
			</control>
			<control type="label"><!-- Episode - Name -->
				<visible>String.IsEmpty(Player.Art(clearlogo))</visible>
				<visible>String.IsEmpty(Player.Art(tvshow.clearlogo))</visible>
				<top>58</top>
				<label>$VAR[OSDSubLabelPVRVar]</label>
				<shadowcolor>text_shadow</shadowcolor>
				<height>100</height>
				<left>373</left>
				<right>0</right>
			</control>
<!-- Plot
			<control type="textbox">
				<left>260</left>
				<top>90</top>
				<right>30</right>
				<height>80</height>
				<label fallback="19055">$INFO[VideoPlayer.Plot]</label>
				<align>justify</align>
				<autoscroll delay="5000" repeat="7500" time="5000"></autoscroll>
				<visible>String.IsEmpty(PVR.EpgEventIcon)</visible>
			</control>
			<control type="textbox">
				<left>260</left>
				<top>90</top>
				<right>260</right>
				<height>80</height>
				<label fallback="19055">$INFO[VideoPlayer.Plot]</label>
				<align>justify</align>
				<autoscroll delay="5000" repeat="7500" time="5000"></autoscroll>
				<visible>!String.IsEmpty(PVR.EpgEventIcon)</visible>
			</control>
-->
			<control type="image">
				<right>30</right>
				<top>20</top>
				<width>200</width>
				<height>200</height>
				<aspectratio aligny="center">keep</aspectratio>
				<texture fallback="DefaultTVShows.png">$INFO[PVR.EpgEventIcon]</texture>
				<visible>!String.IsEmpty(PVR.EpgEventIcon)</visible>
			</control>
			<control type="label"> <!--next EPG Event -->
				<left>373</left>
				<top>180</top>
				<height>25</height>
				<label>[COLOR grey]$LOCALIZE[19031]:[/COLOR] $INFO[VideoPlayer.NextStartTime] - $INFO[VideoPlayer.NextEndTime]: $INFO[VideoPlayer.NextTitle]</label>
				<visible>VideoPlayer.HasEpg + !RDS.HasRadioText</visible>
			</control>
			<control type="label">
				<left>373</left>
				<top>180</top>
				<height>25</height>
				<label>[COLOR grey]$LOCALIZE[14304]: [/COLOR]$INFO[RDS.GetLine(0)]</label>
				<visible>RDS.HasRadioText</visible>
			</control>
		</control>

		<!-- Timeshift -->
		<control type="group">
			<animation effect="fade" time="400">VisibleChange</animation>
			<visible>!Player.ChannelPreviewActive</visible>
			<visible>Player.ShowInfo</visible>
			<control type="group">
				<visible>Player.SeekEnabled | VideoPlayer.HasEPG</visible>
				<control type="label">
					<bottom>205</bottom>
					<right>300</right>
					<width>400</width>
					<height>50</height>
					<align>right</align>
					<aligny>center</aligny>
					<font>font13</font>
					<label>$INFO[PVR.TimeshiftProgressEndTime]</label>
				</control>
				<control type="label">
					<bottom>205</bottom>
					<left>280</left>
					<width>400</width>
					<height>50</height>
					<align>left</align>
					<aligny>center</aligny>
					<font>font13</font>
					<label>$INFO[PVR.TimeshiftProgressStartTime]</label>
				</control>
				<control type="label">
					<bottom>205</bottom>
					<left>280</left>
					<right>280</right>
					<height>50</height>
					<align>center</align>
					<aligny>center</aligny>
					<font>font13</font>
					<label>[B]$LOCALIZE[31026][/B] $INFO[PVR.TimeshiftCur] (-$INFO[PVR.TimeshiftOffset])</label>
					<visible>PVR.IsTimeShift</visible>
				</control>
			</control>
			<control type="group">
				<visible>VideoPlayer.HasEPG</visible>
				<control type="progress">
					<left>280</left>
					<bottom>190</bottom>
					<width>70%</width>
					<height>16</height>
					<info2>PVR.TimeshiftProgressEpgStart</info2>
					<info>PVR.TimeshiftProgressPlayPos</info>
					<texturebg border="3" colordiffuse="60FFFFFF">colors/white50.png</texturebg>
					<midtexture colordiffuse="button_focus">colors/white.png</midtexture>
				</control>
				<control type="progress">
					<left>280</left>
					<bottom>190</bottom>
					<width>70%</width>
					<height>16</height>
					<info2>PVR.TimeshiftProgressPlayPos</info2>
					<info>PVR.TimeshiftProgressEpgEnd</info>
					<texturebg border="3" colordiffuse="00FFFFFF">colors/white50.png</texturebg>
					<midtexture>colors/white50.png</midtexture>
				</control>
			</control>
			<control type="progress">
				<left>280</left>
				<bottom>190</bottom>
				<width>70%</width>
				<height>16</height>
				<info2>PVR.TimeshiftProgressBufferStart</info2>
				<info>PVR.TimeshiftProgressBufferEnd</info>
				<texturebg border="3" colordiffuse="60FFFFFF">colors/white50.png</texturebg>
				<midtexture>colors/white70.png</midtexture>
				<visible>Player.SeekEnabled</visible>
			</control>
		</control>
		<control type="group">
			<animation effect="fade" time="400">VisibleChange</animation>
			<visible>Player.ShowInfo</visible>
			<visible>Player.ChannelPreviewActive</visible>
			<control type="progress">
				<left>280</left>
				<bottom>190</bottom>
				<width>70%</width>
				<height>16</height>
				<info>PVR.EpgEventProgress</info>
				<texturebg border="3" colordiffuse="60FFFFFF">colors/white50.png</texturebg>
				<midtexture colordiffuse="button_focus">colors/white.png</midtexture>
			</control>
		</control>
		<control type="group" id="6001">
			<visible>!Window.IsVisible(playerprocessinfo)</visible>
			<visible>Player.ShowInfo</visible>
			<visible>Player.SeekEnabled</visible>
			<control type="button" id="87">
				<include>HiddenObject</include>
				<onup>200</onup>
				<onunfocus condition="Player.Forwarding | Player.Rewinding">PlayerControl(Play)</onunfocus>
				<ondown>200</ondown>
				<onright>StepForward</onright>
				<onleft>StepBack</onleft>
				<onclick condition="Player.Forwarding | Player.Rewinding">PlayerControl(Play)</onclick>
			</control>
			<control type="slider">
				<bottom>185</bottom>
				<left>280</left>
				<width>70%</width>
				<height>26</height>
				<texturesliderbar colordiffuse="00FFFFFF">osd/progress/nub_bar.png</texturesliderbar>
				<textureslidernib>osd/progress/nub_bar.png</textureslidernib>
				<textureslidernibfocus colordiffuse="button_focus">osd/progress/nub_bar.png</textureslidernibfocus>
				<info>PVR.TimeshiftProgressPlayPos</info>
				<action>pvr.seek</action>
				<visible>!Control.HasFocus(87)</visible>
			</control>
			<control type="slider">
				<bottom>185</bottom>
				<left>280</left>
				<width>70%</width>
				<height>26</height>
				<texturesliderbar colordiffuse="00FFFFFF">osd/progress/nub_bar.png</texturesliderbar>
				<textureslidernib colordiffuse="button_focus">osd/progress/nub_bar.png</textureslidernib>
				<textureslidernibfocus colordiffuse="button_focus">osd/progress/nub_bar.png</textureslidernibfocus>
				<info>PVR.TimeshiftProgressPlayPos</info>
				<action>pvr.seek</action>
				<visible>Control.HasFocus(87)</visible>
			</control>

			<control type="slider">
				<bottom>185</bottom>
				<left>280</left>
				<width>70%</width>
				<height>26</height>
				<texturesliderbar colordiffuse="00FFFFFF">osd/progress/nub_bar.png</texturesliderbar>
				<textureslidernib colordiffuse="button_focus">osd/progress/nub_bar.png</textureslidernib>
				<textureslidernibfocus colordiffuse="button_focus">colors/white.png</textureslidernibfocus>
				<info>PVR.TimeshiftProgressBufferEnd</info>
				<visible>Player.SeekEnabled + !Player.ChannelPreviewActive</visible>
			</control>				
		</control>
	</controls>
</window>

